quantestpy/__init__.py
quantestpy/_version.py
quantestpy/exceptions.py
quantestpy/assertion/assert_ancilla_reset.py
quantestpy/assertion/assert_circuit_equivalent_to_operator.py
quantestpy/assertion/assert_circuit_equivalent_to_output_qubit_state.py
quantestpy/assertion/assert_equivalent_circuits.py
quantestpy/assertion/assert_equivalent_operators.py
quantestpy/assertion/assert_equivalent_state_vectors.py
quantestpy/assertion/assert_normalized_state_vector.py
quantestpy/assertion/assert_qubit_reset_to_zero_state.py
quantestpy/assertion/assert_unary_iteration.py
quantestpy/assertion/assert_unitary_operator.py
quantestpy/assertion/get_ctrl_val.py
quantestpy/assertion/get_tgt_val.py
quantestpy/converter/converter_to_quantestpy_circuit.py
quantestpy/converter/sdk/qasm.py
quantestpy/converter/sdk/qiskit.py
quantestpy/converter/sdk/quri_parts.py
quantestpy/simulator/exceptions.py
quantestpy/simulator/pauli_circuit.py
quantestpy/simulator/quantestpy_circuit.py
quantestpy/simulator/state_vector_circuit.py
quantestpy/visualization/exceptions.py
quantestpy/visualization/pauli_circuit_drawer.py
quantestpy/visualization/quantestpy_circuit_drawer.py
quantestpy/visualization/state_vector_circuit_drawer.py
quantestpy-0.1.2.dist-info/LICENSE
quantestpy-0.1.2.dist-info/METADATA
quantestpy-0.1.2.dist-info/WHEEL
quantestpy-0.1.2.dist-info/top_level.txt
quantestpy-0.1.2.dist-info/RECORD
