Metadata-Version: 2.1
Name: quantestpy
Version: 0.1.2
Summary: Software for testing quantum computing programs.
Author: Quantestpy Development Team
License: Apache 2.0
Project-URL: homepage, https://github.com/QuantestPy/quantestpy
Project-URL: repository, https://github.com/QuantestPy/quantestpy
Requires-Python: >=3.7
License-File: LICENSE
Requires-Dist: numpy (==1.*)
Provides-Extra: ci
Requires-Dist: flake8 (==5.*) ; extra == 'ci'
Requires-Dist: isort (==5.*) ; extra == 'ci'
Requires-Dist: flake8-pyproject ; extra == 'ci'
Provides-Extra: qiskit
Requires-Dist: qiskit (==0.*) ; extra == 'qiskit'
Provides-Extra: quri_parts
Requires-Dist: quri-parts (==0.*) ; extra == 'quri_parts'
Provides-Extra: quri_parts_with_qulacs
Requires-Dist: quri-parts[qulacs] (==0.*) ; extra == 'quri_parts_with_qulacs'
